[
	{
		"name": "Hall Mckay",
		"phone": "(04) 6333 9545",
		"email": "Pellentesque.habitant.morbi@nectempus.net",
		"address ": "4153 Montes, Avenue",
		"id": 26
	},
	{
		"name": "Elijah Watkins",
		"phone": "(01) 0909 4489",
		"email": "Nulla.eget.metus@cubiliaCuraePhasellus.com",
		"address ": "P.O. Box 420, 1099 Enim. Ave",
		"id": 19
	},
	{
		"name": "Hedley Boyer",
		"phone": "(05) 7337 5789",
		"email": "Etiam.bibendum@eget.edu",
		"address ": "Ap #487-8387 Elit, Street",
		"id": 82
	},
	{
		"name": "Warren Thornton",
		"phone": "(08) 4514 0178",
		"email": "est.mauris.rhoncus@pedeCum.org",
		"address ": "1452 Lobortis Ave",
		"id": 75
	},
	{
		"name": "Chadwick Morales",
		"phone": "(04) 2024 6667",
		"email": "pede.ultrices@nectempus.net",
		"address ": "734-1961 Senectus Rd.",
		"id": 26
	},
	{
		"name": "Jelani Ross",
		"phone": "(09) 5837 1329",
		"email": "Cum@arcu.org",
		"address ": "195-9265 In, Rd.",
		"id": 36
	},
	{
		"name": "Hilel Pope",
		"phone": "(01) 0258 0309",
		"email": "ut@eget.net",
		"address ": "519-351 Fringilla St.",
		"id": 27
	},
	{
		"name": "Nehru Frye",
		"phone": "(05) 7158 1769",
		"email": "Aenean.gravida.nunc@estac.edu",
		"address ": "229-8511 Leo. Road",
		"id": 71
	},
	{
		"name": "Thor Sellers",
		"phone": "(05) 1550 8327",
		"email": "aliquet.lobortis.nisi@fringilla.com",
		"address ": "366-4545 Massa. Road",
		"id": 89
	},
	{
		"name": "Rashad Talley",
		"phone": "(07) 8476 8156",
		"email": "tempor.lorem.eget@nonvestibulumnec.com",
		"address ": "Ap #404-2471 Quam Ave",
		"id": 80
	},
	{
		"name": "Hiram Harrison",
		"phone": "(04) 7268 3686",
		"email": "tortor.Integer.aliquam@milacinia.edu",
		"address ": "Ap #420-9481 Nisl. St.",
		"id": 80
	},
	{
		"name": "Walter England",
		"phone": "(04) 3016 2309",
		"email": "lobortis.risus@lectuspede.ca",
		"address ": "Ap #565-3347 Tincidunt St.",
		"id": 11
	},
	{
		"name": "Mannix Blevins",
		"phone": "(03) 5321 5020",
		"email": "ante.bibendum.ullamcorper@purus.com",
		"address ": "5919 Aliquam Av.",
		"id": 19
	},
	{
		"name": "Brent Bailey",
		"phone": "(01) 3653 5862",
		"email": "nisl@nonegestas.edu",
		"address ": "763-5979 Erat. Rd.",
		"id": 34
	},
	{
		"name": "Abraham Dennis",
		"phone": "(07) 4945 7522",
		"email": "pede@sedhendrerit.edu",
		"address ": "8422 Eu Avenue",
		"id": 65
	},
	{
		"name": "Brenden Higgins",
		"phone": "(01) 9456 2118",
		"email": "Aliquam@magnatellus.org",
		"address ": "Ap #813-6274 Tortor St.",
		"id": 54
	},
	{
		"name": "Vincent Chandler",
		"phone": "(08) 1078 4392",
		"email": "amet.ultricies.sem@Sedauctorodio.com",
		"address ": "Ap #508-5214 Lectus. Avenue",
		"id": 59
	},
	{
		"name": "Neville Burton",
		"phone": "(05) 1599 3567",
		"email": "eros.non@temporloremeget.org",
		"address ": "462-3465 Nunc, Rd.",
		"id": 39
	},
	{
		"name": "Avram Terry",
		"phone": "(09) 3220 5331",
		"email": "Aliquam.nisl.Nulla@auctornon.org",
		"address ": "486 Aliquam Rd.",
		"id": 72
	},
	{
		"name": "Joseph Wolfe",
		"phone": "(01) 7013 5819",
		"email": "pede.Nunc@nunc.ca",
		"address ": "P.O. Box 195, 4940 Penatibus Ave",
		"id": 8
	},
	{
		"name": "Ross Brennan",
		"phone": "(05) 9847 0972",
		"email": "amet.ultricies@nonummy.edu",
		"address ": "Ap #155-3189 Tellus. Street",
		"id": 67
	},
	{
		"name": "Baxter Cantu",
		"phone": "(06) 2444 3867",
		"email": "Nunc.sollicitudin@Nullamvitae.org",
		"address ": "Ap #913-5662 Lobortis. Ave",
		"id": 51
	},
	{
		"name": "James Osborn",
		"phone": "(03) 7777 3965",
		"email": "Aenean.massa.Integer@penatibuset.co.uk",
		"address ": "2314 Montes, St.",
		"id": 48
	},
	{
		"name": "Burton Robertson",
		"phone": "(01) 2465 2711",
		"email": "interdum.ligula@risusQuisquelibero.org",
		"address ": "Ap #303-1418 Sollicitudin Rd.",
		"id": 91
	},
	{
		"name": "Keaton Bryan",
		"phone": "(06) 8266 4159",
		"email": "In.condimentum@lectus.edu",
		"address ": "Ap #291-4044 Pharetra Rd.",
		"id": 58
	},
	{
		"name": "Austin Holman",
		"phone": "(02) 1061 1795",
		"email": "vitae.sodales.nisi@Vivamussitamet.com",
		"address ": "9426 Nunc Avenue",
		"id": 33
	},
	{
		"name": "Dennis Mckenzie",
		"phone": "(08) 0216 7825",
		"email": "quam@gravida.com",
		"address ": "819-9893 Nonummy Ave",
		"id": 33
	},
	{
		"name": "Brady Phillips",
		"phone": "(08) 1359 1103",
		"email": "eget@Donec.edu",
		"address ": "893-5545 Placerat Avenue",
		"id": 53
	},
	{
		"name": "Brennan Wong",
		"phone": "(07) 8797 8659",
		"email": "faucibus.ut.nulla@sodaleseliterat.co.uk",
		"address ": "Ap #459-3409 Maecenas Street",
		"id": 31
	},
	{
		"name": "Andrew Henson",
		"phone": "(02) 1693 3426",
		"email": "magna.a.tortor@Aliquamornarelibero.com",
		"address ": "755-823 Malesuada. Av.",
		"id": 96
	},
	{
		"name": "Dante Dalton",
		"phone": "(06) 0978 1767",
		"email": "pede@liberolacusvarius.com",
		"address ": "P.O. Box 625, 9989 Tortor. St.",
		"id": 61
	},
	{
		"name": "Griffin Montoya",
		"phone": "(04) 1552 8458",
		"email": "nec@adipiscing.ca",
		"address ": "616-9085 Lectus. St.",
		"id": 65
	},
	{
		"name": "Quentin Leblanc",
		"phone": "(09) 9144 2734",
		"email": "sodales.Mauris.blandit@sedfacilisisvitae.ca",
		"address ": "P.O. Box 821, 5485 Id Road",
		"id": 93
	},
	{
		"name": "Emery Lindsay",
		"phone": "(06) 3215 7691",
		"email": "orci@magnaNamligula.ca",
		"address ": "153-4633 Ultrices St.",
		"id": 25
	},
	{
		"name": "Keith Banks",
		"phone": "(03) 5392 9623",
		"email": "Mauris.vestibulum.neque@odio.com",
		"address ": "Ap #438-2908 Semper Rd.",
		"id": 16
	},
	{
		"name": "Gareth Howe",
		"phone": "(01) 4955 1719",
		"email": "nulla.magna@fermentumfermentum.org",
		"address ": "7185 Ac Road",
		"id": 99
	},
	{
		"name": "Russell Mcintyre",
		"phone": "(03) 5007 9062",
		"email": "sed.hendrerit@vulputatenisi.ca",
		"address ": "222-8129 Tristique Ave",
		"id": 21
	},
	{
		"name": "Louis Whitley",
		"phone": "(09) 1088 3535",
		"email": "pede.Praesent.eu@iaculisaliquetdiam.org",
		"address ": "9561 Lorem, Ave",
		"id": 3
	},
	{
		"name": "Bernard Lamb",
		"phone": "(08) 4584 8165",
		"email": "erat@Quisque.co.uk",
		"address ": "Ap #606-4643 Malesuada. Avenue",
		"id": 100
	},
	{
		"name": "Cairo Higgins",
		"phone": "(08) 3508 5741",
		"email": "rutrum@magnaPhasellus.org",
		"address ": "641-6913 Ac Street",
		"id": 4
	},
	{
		"name": "Eagan Rasmussen",
		"phone": "(01) 8087 2076",
		"email": "blandit.congue.In@justo.ca",
		"address ": "P.O. Box 606, 1032 Sem, Street",
		"id": 61
	},
	{
		"name": "Nathaniel Bartlett",
		"phone": "(01) 9845 0917",
		"email": "fringilla.ornare@ligulaeu.org",
		"address ": "342 Velit Street",
		"id": 44
	},
	{
		"name": "Graham Strong",
		"phone": "(07) 7662 0849",
		"email": "amet@id.org",
		"address ": "391-9049 Per St.",
		"id": 64
	},
	{
		"name": "Elmo Dalton",
		"phone": "(08) 6197 4126",
		"email": "tincidunt.vehicula@Nunc.net",
		"address ": "P.O. Box 457, 3007 Mauris Rd.",
		"id": 91
	},
	{
		"name": "Brenden Romero",
		"phone": "(06) 7771 7624",
		"email": "magna@magna.net",
		"address ": "Ap #523-8589 Vel Rd.",
		"id": 28
	},
	{
		"name": "Xander Newton",
		"phone": "(03) 9580 1588",
		"email": "egestas@aliquetdiamSed.co.uk",
		"address ": "357-5277 Vitae St.",
		"id": 95
	},
	{
		"name": "Dominic Burton",
		"phone": "(02) 4615 0493",
		"email": "auctor.odio.a@Inornaresagittis.edu",
		"address ": "257-7565 Mi St.",
		"id": 56
	},
	{
		"name": "Ivan Stephens",
		"phone": "(05) 5884 8967",
		"email": "lacus.Mauris.non@venenatis.ca",
		"address ": "307-3366 Magna. Ave",
		"id": 33
	},
	{
		"name": "Prescott Rivera",
		"phone": "(01) 2561 0056",
		"email": "malesuada.augue.ut@ligulatortor.ca",
		"address ": "122 Aenean Avenue",
		"id": 24
	},
	{
		"name": "Kadeem Elliott",
		"phone": "(05) 4618 0772",
		"email": "at.velit@tinciduntvehicularisus.ca",
		"address ": "P.O. Box 323, 2203 Volutpat. Av.",
		"id": 13
	},
	{
		"name": "Amal Henson",
		"phone": "(09) 1316 6927",
		"email": "in@Quisqueaclibero.net",
		"address ": "6983 Nec St.",
		"id": 23
	},
	{
		"name": "Kevin Browning",
		"phone": "(03) 0886 2757",
		"email": "a.malesuada.id@aliquet.co.uk",
		"address ": "8736 Consectetuer Rd.",
		"id": 63
	},
	{
		"name": "Uriel Lynch",
		"phone": "(06) 3426 3369",
		"email": "scelerisque@scelerisquelorem.co.uk",
		"address ": "P.O. Box 809, 3483 Ornare St.",
		"id": 77
	},
	{
		"name": "Kennedy Burt",
		"phone": "(08) 4707 4433",
		"email": "sed.sem.egestas@mollis.net",
		"address ": "468-7460 Sed Av.",
		"id": 72
	},
	{
		"name": "Uriel Baker",
		"phone": "(01) 3005 1242",
		"email": "vitae@tellusnon.co.uk",
		"address ": "991-9973 Erat Av.",
		"id": 30
	},
	{
		"name": "Kelly Brooks",
		"phone": "(06) 9488 2323",
		"email": "semper.cursus@Donec.org",
		"address ": "P.O. Box 754, 3055 Fusce Avenue",
		"id": 78
	},
	{
		"name": "Alfonso Hensley",
		"phone": "(04) 0776 6739",
		"email": "blandit@Donecfeugiat.ca",
		"address ": "724-7624 Eu St.",
		"id": 20
	},
	{
		"name": "Adam Kim",
		"phone": "(09) 7453 9666",
		"email": "tellus@ante.org",
		"address ": "1346 Molestie Avenue",
		"id": 66
	},
	{
		"name": "Edward Navarro",
		"phone": "(09) 5544 8525",
		"email": "per.inceptos.hymenaeos@fermentumconvallis.net",
		"address ": "225 Mauris St.",
		"id": 57
	},
	{
		"name": "Grady Stephenson",
		"phone": "(04) 7980 2480",
		"email": "sem.semper.erat@Integertinciduntaliquam.ca",
		"address ": "8761 Dui. Rd.",
		"id": 75
	},
	{
		"name": "Herman Nixon",
		"phone": "(06) 7593 6542",
		"email": "nulla.at.sem@InfaucibusMorbi.org",
		"address ": "Ap #582-3150 Sit St.",
		"id": 99
	},
	{
		"name": "Addison Mccall",
		"phone": "(07) 3818 6690",
		"email": "ante@auctor.org",
		"address ": "P.O. Box 707, 9938 Ornare Street",
		"id": 81
	},
	{
		"name": "Amos Reynolds",
		"phone": "(07) 1817 0714",
		"email": "aliquet.diam.Sed@Nulla.net",
		"address ": "Ap #181-1841 Eget, Street",
		"id": 34
	},
	{
		"name": "Orson Burch",
		"phone": "(03) 7154 0819",
		"email": "ut.ipsum.ac@eleifend.ca",
		"address ": "4678 Fermentum Rd.",
		"id": 86
	},
	{
		"name": "Travis Roman",
		"phone": "(04) 3221 1283",
		"email": "pellentesque.massa.lobortis@VivamusrhoncusDonec.org",
		"address ": "556-8263 Ut St.",
		"id": 45
	},
	{
		"name": "Lyle Bryan",
		"phone": "(03) 8932 9039",
		"email": "amet.dapibus@neque.org",
		"address ": "9615 Urna Avenue",
		"id": 34
	},
	{
		"name": "Ferris Hendrix",
		"phone": "(03) 1502 6873",
		"email": "ante.Maecenas.mi@fringillamilacinia.edu",
		"address ": "Ap #108-6406 Ligula. Av.",
		"id": 74
	},
	{
		"name": "Abdul Hartman",
		"phone": "(03) 5884 6284",
		"email": "sit@Fusce.edu",
		"address ": "200-9969 Gravida. St.",
		"id": 41
	},
	{
		"name": "Kirk Schneider",
		"phone": "(05) 6341 7037",
		"email": "lacinia.mattis.Integer@idmollis.co.uk",
		"address ": "876 Nec Avenue",
		"id": 11
	},
	{
		"name": "Acton Kennedy",
		"phone": "(02) 4821 6154",
		"email": "vitae.risus@Nullam.edu",
		"address ": "P.O. Box 205, 5683 Et, Av.",
		"id": 90
	},
	{
		"name": "Sebastian Barr",
		"phone": "(02) 4748 1007",
		"email": "Donec.egestas.Duis@pedenonummyut.org",
		"address ": "Ap #312-5980 Et Street",
		"id": 6
	},
	{
		"name": "Lewis Juarez",
		"phone": "(04) 6332 7361",
		"email": "vitae.sodales@luctus.org",
		"address ": "P.O. Box 666, 1549 Etiam Rd.",
		"id": 58
	},
	{
		"name": "Abraham Avery",
		"phone": "(08) 5736 4520",
		"email": "leo.Cras.vehicula@Etiamgravida.ca",
		"address ": "Ap #488-6255 Semper Ave",
		"id": 41
	},
	{
		"name": "Philip Frederick",
		"phone": "(02) 8050 7977",
		"email": "ullamcorper.Duis@Integeraliquam.edu",
		"address ": "P.O. Box 781, 3275 Nonummy. St.",
		"id": 82
	},
	{
		"name": "Jordan Shaw",
		"phone": "(08) 2550 8285",
		"email": "orci@purusin.org",
		"address ": "Ap #305-6023 Luctus Av.",
		"id": 53
	},
	{
		"name": "Elijah Haney",
		"phone": "(04) 5161 1011",
		"email": "lacus@mi.co.uk",
		"address ": "558-219 Quam Avenue",
		"id": 54
	},
	{
		"name": "Oscar Wooten",
		"phone": "(06) 3240 0038",
		"email": "sollicitudin.commodo@venenatisvel.edu",
		"address ": "Ap #438-1089 Massa Av.",
		"id": 20
	},
	{
		"name": "Clark Morales",
		"phone": "(03) 2868 6053",
		"email": "nec.mauris.blandit@tortor.com",
		"address ": "772-9649 Ligula Ave",
		"id": 60
	},
	{
		"name": "Chaney Beck",
		"phone": "(01) 3258 3284",
		"email": "at.pede@suscipit.edu",
		"address ": "Ap #260-8241 Egestas Av.",
		"id": 37
	},
	{
		"name": "Nash Wagner",
		"phone": "(02) 1363 0868",
		"email": "interdum.Sed.auctor@tempuseuligula.edu",
		"address ": "4118 Sit Street",
		"id": 66
	},
	{
		"name": "Clayton Hunter",
		"phone": "(06) 9132 2442",
		"email": "dolor@Aliquam.co.uk",
		"address ": "Ap #618-9937 Consectetuer St.",
		"id": 11
	},
	{
		"name": "Ahmed May",
		"phone": "(07) 6631 9451",
		"email": "enim.diam@Aliquam.com",
		"address ": "P.O. Box 730, 467 Ante St.",
		"id": 59
	},
	{
		"name": "Elijah Talley",
		"phone": "(06) 7806 8591",
		"email": "Vestibulum.ante@mollisPhaselluslibero.ca",
		"address ": "Ap #387-9877 Adipiscing Rd.",
		"id": 70
	},
	{
		"name": "Caleb Evans",
		"phone": "(09) 0272 4942",
		"email": "Etiam.bibendum.fermentum@enimEtiamgravida.net",
		"address ": "2935 Luctus. Rd.",
		"id": 61
	},
	{
		"name": "Finn Alston",
		"phone": "(06) 5252 2009",
		"email": "Sed.eu.eros@eunulla.org",
		"address ": "P.O. Box 297, 7025 Non Rd.",
		"id": 81
	},
	{
		"name": "Adrian Haley",
		"phone": "(01) 6299 0237",
		"email": "ut@tinciduntorci.net",
		"address ": "Ap #705-7356 Fringilla, Rd.",
		"id": 80
	},
	{
		"name": "Damon Reeves",
		"phone": "(03) 5909 6088",
		"email": "vitae.mauris@Quisque.org",
		"address ": "P.O. Box 819, 2390 Augue Ave",
		"id": 53
	},
	{
		"name": "Leo Garza",
		"phone": "(09) 2876 3901",
		"email": "purus@euismod.co.uk",
		"address ": "484-5369 Nonummy Road",
		"id": 8
	},
	{
		"name": "Ezekiel Everett",
		"phone": "(01) 0122 1249",
		"email": "in.aliquet@Proin.co.uk",
		"address ": "Ap #542-7499 Mi Street",
		"id": 3
	},
	{
		"name": "Keefe Patterson",
		"phone": "(05) 6603 0126",
		"email": "erat@pedemalesuada.org",
		"address ": "P.O. Box 452, 1033 Orci. Avenue",
		"id": 53
	},
	{
		"name": "Graiden Bonner",
		"phone": "(04) 7995 3184",
		"email": "urna.et@luctusaliquet.net",
		"address ": "P.O. Box 615, 6033 Sit Ave",
		"id": 10
	},
	{
		"name": "Nissim Dotson",
		"phone": "(06) 2266 8622",
		"email": "et.arcu.imperdiet@rutrum.edu",
		"address ": "P.O. Box 373, 5613 Proin Avenue",
		"id": 25
	},
	{
		"name": "Abbot Bruce",
		"phone": "(02) 4045 1352",
		"email": "odio.sagittis@nequevitaesemper.org",
		"address ": "Ap #845-8375 Ante Ave",
		"id": 12
	},
	{
		"name": "Drew Nelson",
		"phone": "(08) 4107 7190",
		"email": "velit.in@a.org",
		"address ": "576-852 Vitae, Street",
		"id": 94
	},
	{
		"name": "Timon Chang",
		"phone": "(08) 3093 9479",
		"email": "lobortis.tellus@elit.edu",
		"address ": "797-9273 Eget Av.",
		"id": 8
	},
	{
		"name": "Leo West",
		"phone": "(03) 0619 7692",
		"email": "vel@et.ca",
		"address ": "871-5671 Aliquet Street",
		"id": 12
	},
	{
		"name": "Brenden Thompson",
		"phone": "(04) 7073 8563",
		"email": "eu.odio@a.com",
		"address ": "7957 Et Avenue",
		"id": 99
	},
	{
		"name": "Bevis Head",
		"phone": "(03) 4751 4421",
		"email": "Suspendisse@accumsanconvallis.ca",
		"address ": "401-3886 Nisl Av.",
		"id": 14
	},
	{
		"name": "Matthew Morales",
		"phone": "(06) 8421 9546",
		"email": "nec.tempus.mauris@iaculisquispede.net",
		"address ": "P.O. Box 758, 5995 Natoque Street",
		"id": 32
	},
	{
		"name": "Thaddeus Sosa",
		"phone": "(09) 9327 8341",
		"email": "diam.luctus.lobortis@Vivamus.net",
		"address ": "P.O. Box 168, 2491 Tellus. Avenue",
		"id": 21
	}
]